skfeature/__init__.py
skfeature/function/__init__.py
skfeature/function/information_theoretical_based/CIFE.py
skfeature/function/information_theoretical_based/CMIM.py
skfeature/function/information_theoretical_based/DISR.py
skfeature/function/information_theoretical_based/FCBF.py
skfeature/function/information_theoretical_based/ICAP.py
skfeature/function/information_theoretical_based/JMI.py
skfeature/function/information_theoretical_based/LCSI.py
skfeature/function/information_theoretical_based/MIFS.py
skfeature/function/information_theoretical_based/MIM.py
skfeature/function/information_theoretical_based/MRMR.py
skfeature/function/information_theoretical_based/__init__.py
skfeature/function/similarity_based/SPEC.py
skfeature/function/similarity_based/__init__.py
skfeature/function/similarity_based/fisher_score.py
skfeature/function/similarity_based/lap_score.py
skfeature/function/similarity_based/reliefF.py
skfeature/function/similarity_based/trace_ratio.py
skfeature/function/sparse_learning_based/MCFS.py
skfeature/function/sparse_learning_based/NDFS.py
skfeature/function/sparse_learning_based/RFS.py
skfeature/function/sparse_learning_based/UDFS.py
skfeature/function/sparse_learning_based/__init__.py
skfeature/function/sparse_learning_based/ll_l21.py
skfeature/function/sparse_learning_based/ls_l21.py
skfeature/function/statistical_based/CFS.py
skfeature/function/statistical_based/__init__.py
skfeature/function/statistical_based/chi_square.py
skfeature/function/statistical_based/f_score.py
skfeature/function/statistical_based/gini_index.py
skfeature/function/statistical_based/low_variance.py
skfeature/function/statistical_based/t_score.py
skfeature/function/streaming/__init__.py
skfeature/function/streaming/alpha_investing.py
skfeature/function/structure/__init__.py
skfeature/function/structure/graph_fs.py
skfeature/function/structure/group_fs.py
skfeature/function/structure/tree_fs.py
skfeature/function/wrapper/__init__.py
skfeature_chappers-1.1.0.dist-info/LICENSE
skfeature_chappers-1.1.0.dist-info/METADATA
skfeature_chappers-1.1.0.dist-info/WHEEL
skfeature_chappers-1.1.0.dist-info/top_level.txt
skfeature_chappers-1.1.0.dist-info/RECORD
